[
    {
        "race": "g3_all_comers",
        "year": 1984,
        "horse": "アサカシルバー"
    },
    {
        "race": "g3_all_comers",
        "year": 1985,
        "horse": "アサカサイレント"
    },
    {
        "race": "g3_all_comers",
        "year": 1986,
        "horse": "ジュサブロー"
    },
    {
        "race": "g3_all_comers",
        "year": 1987,
        "horse": "ダイナフェアリー"
    },
    {
        "race": "g3_all_comers",
        "year": 1988,
        "horse": "スズパレード"
    },
    {
        "race": "g3_all_comers",
        "year": 1989,
        "horse": "オグリキャップ"
    },
    {
        "race": "g3_all_comers",
        "year": 1990,
        "horse": "ラケットボール"
    },
    {
        "race": "g3_all_comers",
        "year": 1991,
        "horse": "ジョージモナーク"
    },
    {
        "race": "g3_all_comers",
        "year": 1992,
        "horse": "イクノディクタス"
    },
    {
        "race": "g3_all_comers",
        "year": 1993,
        "horse": "ツインターボ"
    },
    {
        "race": "g3_all_comers",
        "year": 1994,
        "horse": "ビワハヤヒデ"
    }
]