[
    {
        "race": "g3_sekiya_kinen",
        "year": 1984,
        "horse": "ハヤテミグ"
    },
    {
        "race": "g3_sekiya_kinen",
        "year": 1985,
        "horse": "タカラスチール"
    },
    {
        "race": "g3_sekiya_kinen",
        "year": 1986,
        "horse": "アイランドゴッテス"
    },
    {
        "race": "g3_sekiya_kinen",
        "year": 1987,
        "horse": "クールハート"
    },
    {
        "race": "g3_sekiya_kinen",
        "year": 1988,
        "horse": "ヒシノリフオー"
    },
    {
        "race": "g3_sekiya_kinen",
        "year": 1989,
        "horse": "ミスターブランディ"
    },
    {
        "race": "g3_sekiya_kinen",
        "year": 1990,
        "horse": "マキバサイクロン"
    },
    {
        "race": "g3_sekiya_kinen",
        "year": 1991,
        "horse": "ニフティニース"
    },
    {
        "race": "g3_sekiya_kinen",
        "year": 1992,
        "horse": "スプライトパッサー"
    },
    {
        "race": "g3_sekiya_kinen",
        "year": 1993,
        "horse": "マイスタージンガー"
    },
    {
        "race": "g3_sekiya_kinen",
        "year": 1994,
        "horse": "マイスーパーマン"
    },
    {
        "race": "g3_sekiya_kinen",
        "year": 1995,
        "horse": "フェスティブキング"
    },
    {
        "race": "g3_sekiya_kinen",
        "year": 1996,
        "horse": "エイシンガイモン"
    },
    {
        "race": "g3_sekiya_kinen",
        "year": 1997,
        "horse": "エイシンガイモン"
    },
    {
        "race": "g3_sekiya_kinen",
        "year": 1998,
        "horse": "ダイワテキサス"
    },
    {
        "race": "g3_sekiya_kinen",
        "year": 1999,
        "horse": "リワードニンファ"
    },
    {
        "race": "g3_sekiya_kinen",
        "year": 2000,
        "horse": "ダイワテキサス"
    },
    {
        "race": "g3_sekiya_kinen",
        "year": 2001,
        "horse": "マグナーテン"
    },
    {
        "race": "g3_sekiya_kinen",
        "year": 2002,
        "horse": "マグナーテン"
    },
    {
        "race": "g3_sekiya_kinen",
        "year": 2003,
        "horse": "オースミコスモ"
    },
    {
        "race": "g3_sekiya_kinen",
        "year": 2004,
        "horse": "ブルーイレヴン"
    },
    {
        "race": "g3_sekiya_kinen",
        "year": 2005,
        "horse": "サイドワインダー"
    },
    {
        "race": "g3_sekiya_kinen",
        "year": 2006,
        "horse": "カンファーベスト"
    },
    {
        "race": "g3_sekiya_kinen",
        "year": 2007,
        "horse": "カンパニー"
    },
    {
        "race": "g3_sekiya_kinen",
        "year": 2008,
        "horse": "マルカシェンク"
    },
    {
        "race": "g3_sekiya_kinen",
        "year": 2009,
        "horse": "スマイルジャック"
    },
    {
        "race": "g3_sekiya_kinen",
        "year": 2010,
        "horse": "レッツゴーキリシマ"
    },
    {
        "race": "g3_sekiya_kinen",
        "year": 2011,
        "horse": "レインボーペガサス"
    },
    {
        "race": "g3_sekiya_kinen",
        "year": 2012,
        "horse": "ドナウブルー"
    },
    {
        "race": "g3_sekiya_kinen",
        "year": 2013,
        "horse": "レッドスパーダ"
    },
    {
        "race": "g3_sekiya_kinen",
        "year": 2014,
        "horse": "クラレント"
    },
    {
        "race": "g3_sekiya_kinen",
        "year": 2015,
        "horse": "レッドアリオン"
    },
    {
        "race": "g3_sekiya_kinen",
        "year": 2016,
        "horse": "ヤングマンパワー"
    },
    {
        "race": "g3_sekiya_kinen",
        "year": 2017,
        "horse": "マルターズアポジー"
    },
    {
        "race": "g3_sekiya_kinen",
        "year": 2018,
        "horse": "プリモシーン"
    },
    {
        "race": "g3_sekiya_kinen",
        "year": 2019,
        "horse": "ミッキーグローリー"
    },
    {
        "race": "g3_sekiya_kinen",
        "year": 2020,
        "horse": "サトノアーサー"
    },
    {
        "race": "g3_sekiya_kinen",
        "year": 2021,
        "horse": "ロータスランド"
    },
    {
        "race": "g3_sekiya_kinen",
        "year": 2022,
        "horse": "ウインカーネリアン"
    }
]